{
"nodes":[
{"id":0,"label":"0","group":0,"x":56.808884,"y":-112.985558},
{"id":1,"label":"1","group":1,"x":-428.438202,"y":-176.775162},
{"id":2,"label":"2","group":2,"x":179.315567,"y":479.069092},
{"id":3,"label":"3","group":3,"x":369.525787,"y":136.956467},
{"id":4,"label":"4","group":4,"x":-49.400112,"y":84.214378},
{"id":5,"label":"5","group":5,"x":241.072189,"y":-21.350264},
{"id":6,"label":"6","group":6,"x":2.211788,"y":215.781387},
{"id":7,"label":"7","group":7,"x":-296.007019,"y":-4.869017},
{"id":8,"label":"8","group":8,"x":-199.706940,"y":-20.060671},
{"id":9,"label":"9","group":9,"x":-5.669882,"y":-35.601566},
{"id":10,"label":"10","group":10,"x":-158.445953,"y":-58.341846},
{"id":11,"label":"11","group":11,"x":-80.713074,"y":-179.690887},
{"id":12,"label":"12","group":12,"x":91.886803,"y":209.206802},
{"id":13,"label":"13","group":13,"x":125.670288,"y":66.945572},
{"id":14,"label":"14","group":14,"x":274.055542,"y":330.667145},
{"id":15,"label":"15","group":15,"x":-401.176178,"y":323.606995}
],
"edges":[
{"from":0,"to":0},
{"from":1,"to":1},
{"from":2,"to":2},
{"from":3,"to":3},
{"from":4,"to":4},
{"from":5,"to":5},
{"from":6,"to":6},
{"from":7,"to":7},
{"from":8,"to":8},
{"from":9,"to":9},
{"from":10,"to":10},
{"from":11,"to":11},
{"from":12,"to":12},
{"from":13,"to":13},
{"from":14,"to":14},
{"from":15,"to":15},
{"from":0,"to":4},
{"from":0,"to":6},
{"from":0,"to":9},
{"from":0,"to":13},
{"from":6,"to":4},
{"from":6,"to":3},
{"from":6,"to":5},
{"from":6,"to":13},
{"from":6,"to":14},
{"from":6,"to":9},
{"from":9,"to":7},
{"from":9,"to":10},
{"from":0,"to":5},
{"from":4,"to":3},
{"from":4,"to":1},
{"from":4,"to":15},
{"from":4,"to":9},
{"from":4,"to":5},
{"from":4,"to":14},
{"from":2,"to":14},
{"from":2,"to":13},
{"from":5,"to":3},
{"from":5,"to":9},
{"from":5,"to":13},
{"from":14,"to":5},
{"from":14,"to":3},
{"from":6,"to":11},
{"from":13,"to":9},
{"from":13,"to":11},
{"from":13,"to":12},
{"from":9,"to":8},
{"from":8,"to":10},
{"from":7,"to":10},
{"from":11,"to":12}
]
}
